ffprint/__init__.py
ffprint/core.py
ffprint-1.0.0.dist-info/LICENSE.license
ffprint-1.0.0.dist-info/METADATA
ffprint-1.0.0.dist-info/WHEEL
ffprint-1.0.0.dist-info/top_level.txt
ffprint-1.0.0.dist-info/RECORD
