Metadata-Version: 2.1
Name: ffprint
Version: 1.0.0
Summary: self-defined print
Author: eric.gao
Author-email: 18655035787@163.com
Requires-Python: >=3.6
License-File: LICENSE.license
Requires-Dist: loguru ==0.7.2
